{
  "number": 992,
  "name": "Iron Hands",
  "base_hp": 8,
  "strength": "3/7",
  "dexterity": "2/4",
  "vitality": "3/6",
  "special": "2/4",
  "insight": "2/4",
  "moves": {
    "bronze": [],
    "silver": [],
    "gold": ["Sand Attack", "Tackle", "Focus Energy", "Arm Thrust", "Electric Terrain", "Fake Out", "Whirlwind", "Thunder Punch", "Slam", "Force Palm", "Seismic Toss", "Charge", "Wild Charge", "Close Combat", "Detect", "Heavy Slam", "Belly Drum", "Focus Punch"],
    "platinum": [],
    "diamond": []
  }
}
